{
  "kaynak": "Kapalı Çarşı",
  "fetched_at_utc": "2026-03-15T10:16:52+00:00",
  "count": 5,
  "rows": [
    {
      "kaynak": "Kapalı Çarşı",
      "altin_adi": "Gram Altın",
      "alis_fiyati": 7234.986,
      "satis_fiyati": 7235.796,
      "gunluk_degisim_yuzde": 0.41,
      "guncellenme_tarihi": "2026-03-13T10:27:59.487Z"
    },
    {
      "kaynak": "Kapalı Çarşı",
      "altin_adi": "Çeyrek Altın",
      "alis_fiyati": 11627.35,
      "satis_fiyati": 11898.89,
      "gunluk_degisim_yuzde": -1.17,
      "guncellenme_tarihi": "2026-03-13T10:02:17.822Z"
    },
    {
      "kaynak": "Kapalı Çarşı",
      "altin_adi": "Yarım Altın",
      "alis_fiyati": 23182.03,
      "satis_fiyati": 23797.78,
      "gunluk_degisim_yuzde": -1.17,
      "guncellenme_tarihi": "2026-03-13T10:02:17.822Z"
    },
    {
      "kaynak": "Kapalı Çarşı",
      "altin_adi": "Cumhuriyet Altını",
      "alis_fiyati": 48164.0,
      "satis_fiyati": 48892.0,
      "gunluk_degisim_yuzde": -1.31,
      "guncellenme_tarihi": "2026-03-13T09:24:31.280Z"
    },
    {
      "kaynak": "ENUYGUN Finans",
      "altin_adi": "Altın (Ons/USD)",
      "alis_fiyati": 5010.75582184038,
      "satis_fiyati": 5023.731464737793,
      "gunluk_degisim_yuzde": -0.98,
      "guncellenme_tarihi": "2026-03-13T20:59:45.626Z"
    }
  ]
}
